triangler/__init__.py
triangler/__main__.py
triangler/cmd.py
triangler/color.py
triangler/edges.py
triangler/mod.py
triangler/process.py
triangler/sampling.py
triangler_patch-0.1.3.dist-info/LICENSE
triangler_patch-0.1.3.dist-info/WHEEL
triangler_patch-0.1.3.dist-info/METADATA
triangler_patch-0.1.3.dist-info/RECORD
