Metadata-Version: 2.1
Name: triangler-patch
Version: 0.1.3
Summary: triangler dependencies version patch
Home-page: https://github.com/tdh8316/triangler
Author: djkcyl
Author-email: cyl@cyllive.cn
Requires-Python: >=3.9,<3.10
Classifier: Programming Language :: Python :: 3
Classifier: Programming Language :: Python :: 3.9
Requires-Dist: scikit-image (>=0.19.0,<0.20.0)
Project-URL: Repository, https://github.com/tdh8316/triangler
